ncolony/__init__.py
ncolony/__main__.py
ncolony/beatcheck.py
ncolony/ctllib.py
ncolony/directory_monitor.py
ncolony/httpcheck.py
ncolony/interfaces.py
ncolony/process_events.py
ncolony/schedulelib.py
ncolony/service.py
ncolony/client/__init__.py
ncolony/client/heart.py
ncolony/client/tests/__init__.py
ncolony/client/tests/test_heart.py
ncolony/tests/__init__.py
ncolony/tests/functional_test.py
ncolony/tests/helper.py
ncolony/tests/test_beatcheck.py
ncolony/tests/test_ctllib.py
ncolony/tests/test_directory_monitor.py
ncolony/tests/test_httpcheck.py
ncolony/tests/test_process_events.py
ncolony/tests/test_schedulelib.py
ncolony/tests/test_service.py
ncolony/tests/test_twistd_plugin.py
twisted/plugins/ncolony_beatcheck.py
twisted/plugins/ncolony_schedulelib.py
twisted/plugins/ncolony_service.py
ncolony-2024.1.11.74140.dist-info/LICENSE
ncolony-2024.1.11.74140.dist-info/METADATA
ncolony-2024.1.11.74140.dist-info/WHEEL
ncolony-2024.1.11.74140.dist-info/entry_points.txt
ncolony-2024.1.11.74140.dist-info/top_level.txt
ncolony-2024.1.11.74140.dist-info/RECORD
