Metadata-Version: 2.1
Name: ncolony
Version: 2024.1.11.74140
Summary: A wrapper around Twisted process monitor which allows runtime configuration via file-based communication
Author-email: Moshe Zadka <moshez@zadka.club>
License: Permission is hereby granted, free of charge, to any person obtaining a
Project-URL: Homepage, https://github.com/ncolony/ncolony
Requires-Python: >=3.11
License-File: LICENSE
Requires-Dist: twisted
Requires-Dist: gather
Provides-Extra: docs
Requires-Dist: sphinx ; extra == 'docs'
Provides-Extra: lint
Requires-Dist: flake8 ; extra == 'lint'
Requires-Dist: black ; extra == 'lint'
Requires-Dist: pylint ; extra == 'lint'
Provides-Extra: mypy
Requires-Dist: mypy ; extra == 'mypy'
Provides-Extra: tests
Requires-Dist: coverage[toml] ; extra == 'tests'
